topsis_vani_102303064/__init__.py
topsis_vani_102303064/pred_as1.py
topsis_vani_102303064-1.0.3.dist-info/licenses/LICENSE
topsis_vani_102303064-1.0.3.dist-info/METADATA
topsis_vani_102303064-1.0.3.dist-info/WHEEL
topsis_vani_102303064-1.0.3.dist-info/entry_points.txt
topsis_vani_102303064-1.0.3.dist-info/top_level.txt
topsis_vani_102303064-1.0.3.dist-info/RECORD
