Metadata-Version: 2.4
Name: topsis-vani-102303064
Version: 1.0.3
Summary: TOPSIS implementation as a Python package
Author: Vani
Author-email: vanimohindru7@gmail.com
License: MIT
Requires-Python: >=3.8
License-File: LICENSE
Requires-Dist: pandas
Requires-Dist: numpy
Dynamic: author
Dynamic: author-email
Dynamic: description
Dynamic: description-content-type
Dynamic: license
Dynamic: license-file
Dynamic: requires-dist
Dynamic: requires-python
Dynamic: summary
